expenselm_mcp/__init__.py
expenselm_mcp/server.py
expenselm_mcp-0.1.0.dist-info/METADATA
expenselm_mcp-0.1.0.dist-info/WHEEL
expenselm_mcp-0.1.0.dist-info/entry_points.txt
expenselm_mcp-0.1.0.dist-info/RECORD
