Metadata-Version: 2.4
Name: expenselm-mcp
Version: 0.1.0
Summary: ExpenseLM MCP Server
Requires-Python: >=3.12
Requires-Dist: fastmcp>=2.10.6
Requires-Dist: httpx>=0.28.1
